bnpm/__init__.py
bnpm/automatic_regression.py
bnpm/ca2p_preprocessing.py
bnpm/circular.py
bnpm/classification.py
bnpm/clustering.py
bnpm/container_helpers.py
bnpm/cross_validation.py
bnpm/cupy_helpers.py
bnpm/decomposition.py
bnpm/email_helpers.py
bnpm/featurization.py
bnpm/file_helpers.py
bnpm/h5_handling.py
bnpm/image_augmentation.py
bnpm/image_processing.py
bnpm/indexing.py
bnpm/linear_regression.py
bnpm/math_functions.py
bnpm/misc.py
bnpm/neural_networks.py
bnpm/optimization.py
bnpm/other_peoples_code.py
bnpm/parallel_helpers.py
bnpm/path_helpers.py
bnpm/plotting_helpers.py
bnpm/resource_tracking.py
bnpm/server.py
bnpm/similarity.py
bnpm/spectral.py
bnpm/sql_helpers.py
bnpm/stats.py
bnpm/testing.py
bnpm/timeSeries.py
bnpm/torch_helpers.py
bnpm/video.py
bnpm/welford_moving.py
bnpm/welford_moving_2D.py
bnpm-0.6.6.dist-info/licenses/LICENSE
bnpm-0.6.6.dist-info/METADATA
bnpm-0.6.6.dist-info/WHEEL
bnpm-0.6.6.dist-info/top_level.txt
bnpm-0.6.6.dist-info/RECORD
